kagent/langgraph/__init__.py
kagent/langgraph/_a2a.py
kagent/langgraph/_checkpointer.py
kagent/langgraph/_converters.py
kagent/langgraph/_error_mappings.py
kagent/langgraph/_executor.py
kagent/langgraph/_metadata_utils.py
kagent_langgraph-0.7.8.dist-info/METADATA
kagent_langgraph-0.7.8.dist-info/WHEEL
kagent_langgraph-0.7.8.dist-info/top_level.txt
kagent_langgraph-0.7.8.dist-info/RECORD
