Metadata-Version: 2.4
Name: kagent-langgraph
Version: 0.7.8
Summary: LangGraph integration for KAgent with A2A server support
Requires-Python: >=3.13
Requires-Dist: langgraph>=0.6.5
Requires-Dist: langchain-core>=0.3.0
Requires-Dist: httpx>=0.25.0
Requires-Dist: fastapi>=0.100.0
Requires-Dist: pydantic>=2.0.0
Requires-Dist: typing-extensions>=4.0.0
Requires-Dist: uvicorn>=0.20.0
Requires-Dist: a2a-sdk>=0.2.16
Requires-Dist: kagent-core
Requires-Dist: langsmith[otel]>=0.4.30
Provides-Extra: dev
Requires-Dist: pytest>=7.0.0; extra == "dev"
Requires-Dist: pytest-asyncio>=0.21.0; extra == "dev"
Requires-Dist: black>=23.0.0; extra == "dev"
Requires-Dist: ruff>=0.1.0; extra == "dev"
